influxdb_lite/__init__.py
influxdb_lite/attributes.py
influxdb_lite/client.py
influxdb_lite/measurement.py
influxdblite-0.1.6.dist-info/LICENSE
influxdblite-0.1.6.dist-info/METADATA
influxdblite-0.1.6.dist-info/WHEEL
influxdblite-0.1.6.dist-info/top_level.txt
influxdblite-0.1.6.dist-info/RECORD
