Metadata-Version: 2.1
Name: influxdblite
Version: 0.1.6
Summary: A basic python ORM for InfluxDB OSS 2.x.
Home-page: https://github.com/perrytec/influxdb_lite.git
Author: perrytec
Author-email: rodrigo.troncoso@perry.sg
Classifier: Programming Language :: Python :: 3
Classifier: License :: OSI Approved :: MIT License
Classifier: Operating System :: OS Independent
Requires-Python: >=3.6
License-File: LICENSE
Requires-Dist: influxdb-client
Requires-Dist: ciso8601
